{"cameraMode":{"drawMode":0,"name":"Shaded","section":"Shading Mode"},"sceneLighting":true,"audioPlay":false,"sceneViewState":{"m_AlwaysRefresh":false,"showFog":true,"showSkybox":true,"showFlares":true,"showImageEffects":true,"showParticleSystems":true,"showVisualEffectGraphs":true,"m_FxEnabled":true},"in2DMode":false,"pivot":{"x":-1.2155768871307374,"y":0.8929121494293213,"z":-0.30343905091285708},"rotation":{"x":-0.13593789935112,"y":0.7385649085044861,"z":-0.15650056302547456,"w":-0.6415252685546875},"size":13.145447731018067,"orthographic":false}